pyCribbageApp/CribbageApp.py
pyCribbageApp/__init__.py
pyCribbageApp/tkCribbageViewManager.py
pycribbageapp-0.1.4.data/data/Help/pyCribbageApp/pyCribbageApp_HelpFile.txt
pycribbageapp-0.1.4.dist-info/METADATA
pycribbageapp-0.1.4.dist-info/WHEEL
pycribbageapp-0.1.4.dist-info/entry_points.txt
pycribbageapp-0.1.4.dist-info/licenses/LICENSE
pycribbageapp-0.1.4.dist-info/RECORD
