Metadata-Version: 2.4
Name: pyCribbageApp
Version: 0.1.4
Summary: pyCribbageApp is a python package that provides a tkinter based GUI for playing cribbage games using the CribbageSim package.
Keywords: GUI,cribbage,tkinter,desktop
Author-Email: "Kevin R. Geurts" <kevin.r.geurts@gmail.com>
License-Expression: MIT
License-File: LICENSE
Classifier: Programming Language :: Python :: 3
Classifier: Operating System :: OS Independent
Classifier: Development Status :: 5 - Production/Stable
Classifier: Environment :: Win32 (MS Windows)
Classifier: Environment :: X11 Applications
Classifier: Intended Audience :: End Users/Desktop
Classifier: Topic :: Games/Entertainment :: Turn Based Strategy
Project-URL: Homepage, https://github.com/KevinRGeurts/pyCribbageApp
Project-URL: Issues, https://github.com/KevinRGeurts/pyCribbageApp/issues
Requires-Python: >=3.12
Requires-Dist: tkAppFramework>=0.9.3
Requires-Dist: CribbageSim>=1.0.2
